[
  {
    "exercise_name": "grocery-shopping",
    "started_at": 1768382859.428275,
    "completed_at": 1768382861.878944,
    "comments": [
      "Great work! You have successfully used `git add` and `git commit` to modify the shopping list! Keep it up!"
    ],
    "status": "Completed"
  },
  {
    "exercise_name": "log-and-order",
    "started_at": 1768384731.770268,
    "completed_at": 1768384733.381432,
    "comments": [],
    "status": "Completed"
  },
  {
    "exercise_name": "stage-fright",
    "started_at": 1768381899.394646,
    "completed_at": 1768381901.620914,
    "comments": [
      "Great work! You have successfully checked in all the actors!"
    ],
    "status": "Completed"
  },
  {
    "exercise_name": "staging-intervention",
    "started_at": 1768382584.377865,
    "completed_at": 1768382586.270082,
    "comments": [
      "Great work! You have successfully fixed the attendance system!"
    ],
    "status": "Completed"
  },
  {
    "exercise_name": "under-control",
    "started_at": 1768380288.416362,
    "completed_at": 1768380290.116637,
    "comments": [
      "You successfully used git init to initialize this folder as a Git repository!"
    ],
    "status": "Completed"
  },
  {
    "exercise_name": "undo-init",
    "started_at": 1768380627.743463,
    "completed_at": 1768380630.253149,
    "comments": [
      "You have successfully undone the init operation!"
    ],
    "status": "Completed"
  },
  {
    "exercise_name": "remote-control",
    "started_at": 1768977512.972633,
    "completed_at": 1768977586.15759,
    "comments": [
      "That is not the right Github url!"
    ],
    "status": "Incomplete"
  },
  {
    "exercise_name": "remote-control",
    "started_at": 1768977615.095966,
    "completed_at": 1768977625.018811,
    "comments": [
      "Great work setting up a public remote repository!"
    ],
    "status": "Completed"
  },
  {
    "exercise_name": "link-me",
    "started_at": 1768978291.21537,
    "completed_at": 1768978292.731252,
    "comments": [
      "Great work with using git remote to add an upstream remote!"
    ],
    "status": "Completed"
  },
  {
    "exercise_name": "push-over",
    "started_at": 1768980035.933973,
    "completed_at": 1768980041.184335,
    "comments": [
      "Great work pushing changes to the remote!"
    ],
    "status": "Completed"
  }
]